src/__init__.py
src/deadOrNot.py
src/fileReader.py
tests/__init__.py
tests/test_fileReader_ignoreFile.py
tests/test_fileReader_link.py
tests/test_fileReader_textFile.py
DeadOrNot-1.0.2.dist-info/LICENSE
DeadOrNot-1.0.2.dist-info/METADATA
DeadOrNot-1.0.2.dist-info/WHEEL
DeadOrNot-1.0.2.dist-info/entry_points.txt
DeadOrNot-1.0.2.dist-info/top_level.txt
DeadOrNot-1.0.2.dist-info/RECORD
