Metadata-Version: 2.1
Name: DeadOrNot
Version: 1.0.2
Summary: A command-line tool for reporting on the status of links in a file
Home-page: https://github.com/AbdulMAbdi/deadOrNot
Author: Abdul Abdi
Author-email: aabdi39@myseneca.ca
License: MIT
Platform: UNKNOWN
Classifier: Programming Language :: Python :: 3
Classifier: License :: OSI Approved :: MIT License
Classifier: Operating System :: OS Independent
Requires-Python: >=3.6
Requires-Dist: colorama
Requires-Dist: requests
Requires-Dist: termcolor
Requires-Dist: pytest
Requires-Dist: pre-commit
Requires-Dist: black
Requires-Dist: flake8
Requires-Dist: requests-mock
Requires-Dist: pytest-cov
